<?xml version="1.0" encoding="UTF-8" standalone="yes"?>
<LOGGING>
  <logging_type>Trend</logging_type>
  <vender_id>Infinity Prospect</vender_id>
  <vender>Maintek Enterprise</vender>
  <station_ref>324ec5c82df5f05a7c733b66b757de03e3c465d6aaad61bef3b5e72bdf7632f3</station_ref>
  <station_id>kel-tcg-007</station_id>
  <station_name>Pasir Mas</station_name>
  <send_date>
    <year>2024</year>
    <month>02</month>
    <day>15</day>
  </send_date>
  <send_time>
    <hour>12</hour>
    <minute>39</minute>
    <second>58</second>
  </send_time>
  <total_data>152</total_data>
  <logging>
    <data1>2024-02-15,00:00:00,6.55,6.86,,9,7,,91199,,93399,,92299</data1>
    <data2>2024-02-15,00:05:00,6.54,6.86,,9,7,,91199,,93399,,92299</data2>
    <data3>2024-02-15,00:10:00,6.54,6.86,,9,7,,91199,,93399,,92299</data3>
    <data4>2024-02-15,00:15:00,6.54,6.86,,9,7,,91199,,93399,,92299</data4>
    <data5>2024-02-15,00:20:00,6.54,6.86,,9,7,,91199,,93399,,92299</data5>
    <data6>2024-02-15,00:25:00,6.54,6.86,,9,7,,91199,,93399,,92299</data6>
    <data7>2024-02-15,00:30:00,6.54,6.85,,9,7,,91199,,93399,,92299</data7>
    <data8>2024-02-15,00:35:00,6.54,6.86,,9,7,,91199,,93399,,92299</data8>
    <data9>2024-02-15,00:40:00,6.55,6.86,,9,7,,91199,,93399,,92299</data9>
    <data10>2024-02-15,00:45:00,6.55,6.86,,9,7,,91199,,93399,,92299</data10>
    <data11>2024-02-15,00:50:00,6.54,6.86,,9,7,,91199,,93399,,92299</data11>
    <data12>2024-02-15,00:55:00,6.55,6.85,,9,7,,91199,,93399,,92299</data12>
    <data13>2024-02-15,01:00:00,6.54,6.86,,9,7,,91199,,93399,,92299</data13>
    <data14>2024-02-15,01:05:00,6.55,6.86,,9,7,,91199,,93399,,92299</data14>
    <data15>2024-02-15,01:10:00,6.54,6.86,,9,7,,91199,,93399,,92299</data15>
    <data16>2024-02-15,01:15:00,6.54,6.85,,9,7,,91199,,93399,,92299</data16>
    <data17>2024-02-15,01:20:00,6.54,6.85,,9,7,,91199,,93399,,92299</data17>
    <data18>2024-02-15,01:25:00,6.54,6.86,,9,7,,91199,,93399,,92299</data18>
    <data19>2024-02-15,01:30:00,6.54,6.86,,9,7,,91199,,93399,,92299</data19>
    <data20>2024-02-15,01:35:00,6.55,6.86,,9,7,,91199,,93399,,92299</data20>
    <data21>2024-02-15,01:40:00,6.55,6.86,,9,7,,91199,,93399,,92299</data21>
    <data22>2024-02-15,01:45:00,6.54,6.86,,9,7,,91199,,93399,,92299</data22>
    <data23>2024-02-15,01:50:00,6.54,6.86,,9,7,,91199,,93399,,92299</data23>
    <data24>2024-02-15,01:55:00,6.54,6.86,,9,7,,91199,,93399,,92299</data24>
    <data25>2024-02-15,02:00:00,6.54,6.86,,9,7,,91199,,93399,,92299</data25>
    <data26>2024-02-15,02:05:00,6.54,6.86,,9,7,,91199,,93399,,92299</data26>
    <data27>2024-02-15,02:10:00,6.54,6.86,,9,7,,91199,,93399,,92299</data27>
    <data28>2024-02-15,02:15:00,6.55,6.86,,9,7,,91199,,93399,,92299</data28>
    <data29>2024-02-15,02:20:00,6.55,6.86,,9,7,,91199,,93399,,92299</data29>
    <data30>2024-02-15,02:25:00,6.54,6.86,,9,7,,91199,,93399,,92299</data30>
    <data31>2024-02-15,02:30:00,6.54,6.86,,9,7,,91199,,93399,,92299</data31>
    <data32>2024-02-15,02:35:00,6.54,6.86,,9,7,,91199,,93399,,92299</data32>
    <data33>2024-02-15,02:40:00,6.54,6.85,,9,7,,91199,,93399,,92299</data33>
    <data34>2024-02-15,02:45:00,6.54,6.86,,9,7,,91199,,93399,,92299</data34>
    <data35>2024-02-15,02:50:00,6.54,6.85,,9,7,,91199,,93399,,92299</data35>
    <data36>2024-02-15,02:55:00,6.54,6.85,,9,7,,91199,,93399,,92299</data36>
    <data37>2024-02-15,03:00:00,6.54,6.85,,9,7,,91199,,93399,,92299</data37>
    <data38>2024-02-15,03:05:00,6.55,6.85,,9,7,,91199,,93399,,92299</data38>
    <data39>2024-02-15,03:10:00,6.54,6.85,,9,7,,91199,,93399,,92299</data39>
    <data40>2024-02-15,03:15:00,6.55,6.85,,9,7,,91199,,93399,,92299</data40>
    <data41>2024-02-15,03:20:00,6.55,6.85,,9,7,,91199,,93399,,92299</data41>
    <data42>2024-02-15,03:25:00,6.54,6.85,,9,7,,91199,,93399,,92299</data42>
    <data43>2024-02-15,03:30:00,6.54,6.85,,9,7,,91199,,93399,,92299</data43>
    <data44>2024-02-15,03:35:00,6.55,6.85,,9,7,,91199,,93399,,92299</data44>
    <data45>2024-02-15,03:40:00,6.55,6.85,,9,7,,91199,,93399,,92299</data45>
    <data46>2024-02-15,03:45:00,6.55,6.85,,9,7,,91199,,93399,,92299</data46>
    <data47>2024-02-15,03:50:00,6.55,6.85,,9,7,,91199,,93399,,92299</data47>
    <data48>2024-02-15,03:55:00,6.54,6.85,,9,7,,91199,,93399,,92299</data48>
    <data49>2024-02-15,04:00:00,6.54,6.85,,9,7,,91199,,93399,,92299</data49>
    <data50>2024-02-15,04:05:00,6.55,6.85,,9,7,,91199,,93399,,92299</data50>
    <data51>2024-02-15,04:10:00,6.55,6.85,,9,7,,91199,,93399,,92299</data51>
    <data52>2024-02-15,04:15:00,6.55,6.86,,9,7,,91199,,93399,,92299</data52>
    <data53>2024-02-15,04:20:00,6.55,6.85,,9,7,,91199,,93399,,92299</data53>
    <data54>2024-02-15,04:25:00,6.55,6.85,,9,7,,91199,,93399,,92299</data54>
    <data55>2024-02-15,04:30:00,6.55,6.85,,9,7,,91199,,93399,,92299</data55>
    <data56>2024-02-15,04:35:00,6.54,6.85,,9,7,,91199,,93399,,92299</data56>
    <data57>2024-02-15,04:40:00,6.55,6.85,,9,7,,91199,,93399,,92299</data57>
    <data58>2024-02-15,04:45:00,6.55,6.85,,9,7,,91199,,93399,,92299</data58>
    <data59>2024-02-15,04:50:00,6.54,6.85,,9,7,,91199,,93399,,92299</data59>
    <data60>2024-02-15,04:55:00,6.54,6.85,,9,7,,91199,,93399,,92299</data60>
    <data61>2024-02-15,05:00:00,6.55,6.85,,9,7,,91199,,93399,,92299</data61>
    <data62>2024-02-15,05:05:00,6.54,6.85,,9,7,,91199,,93399,,92299</data62>
    <data63>2024-02-15,05:10:00,6.55,6.85,,9,7,,91199,,93399,,92299</data63>
    <data64>2024-02-15,05:15:00,6.54,6.85,,9,7,,91199,,93399,,92299</data64>
    <data65>2024-02-15,05:20:00,6.54,6.85,,9,7,,91199,,93399,,92299</data65>
    <data66>2024-02-15,05:25:00,6.54,6.85,,9,7,,91199,,93399,,92299</data66>
    <data67>2024-02-15,05:30:00,6.55,6.85,,9,7,,91199,,93399,,92299</data67>
    <data68>2024-02-15,05:35:00,6.54,6.85,,9,7,,91199,,93399,,92299</data68>
    <data69>2024-02-15,05:40:00,6.54,6.85,,9,7,,91199,,93399,,92299</data69>
    <data70>2024-02-15,05:45:00,6.54,6.85,,9,7,,91199,,93399,,92299</data70>
    <data71>2024-02-15,05:50:00,6.54,6.85,,9,7,,91199,,93399,,92299</data71>
    <data72>2024-02-15,05:55:00,6.54,6.85,,9,7,,91199,,93399,,92299</data72>
    <data73>2024-02-15,06:00:00,6.54,6.85,,9,7,,91199,,93399,,92299</data73>
    <data74>2024-02-15,06:05:00,6.54,6.85,,9,7,,91199,,93399,,92299</data74>
    <data75>2024-02-15,06:10:00,6.55,6.86,,9,7,,91199,,93399,,92299</data75>
    <data76>2024-02-15,06:15:00,6.55,6.86,,9,7,,91199,,93399,,92299</data76>
    <data77>2024-02-15,06:20:00,6.55,6.85,,9,7,,91199,,93399,,92299</data77>
    <data78>2024-02-15,06:25:00,6.54,6.86,,9,7,,91199,,93399,,92299</data78>
    <data79>2024-02-15,06:30:00,6.54,6.86,,9,7,,91199,,93399,,92299</data79>
    <data80>2024-02-15,06:35:00,6.54,6.85,,9,7,,91199,,93399,,92299</data80>
    <data81>2024-02-15,06:40:00,6.54,6.85,,9,7,,91199,,93399,,92299</data81>
    <data82>2024-02-15,06:45:00,6.54,6.85,,9,7,,91199,,93399,,92299</data82>
    <data83>2024-02-15,06:50:00,6.55,6.86,,9,7,,91199,,93399,,92299</data83>
    <data84>2024-02-15,06:55:00,6.54,6.85,,9,7,,91199,,93399,,92299</data84>
    <data85>2024-02-15,07:00:00,6.55,6.85,,9,7,,91199,,93399,,92299</data85>
    <data86>2024-02-15,07:05:00,6.54,6.85,,9,7,,91199,,93399,,92299</data86>
    <data87>2024-02-15,07:10:00,6.54,6.85,,9,7,,91199,,93399,,92299</data87>
    <data88>2024-02-15,07:15:00,6.54,6.85,,9,7,,91199,,93399,,92299</data88>
    <data89>2024-02-15,07:20:00,6.55,6.85,,9,7,,91199,,93399,,92299</data89>
    <data90>2024-02-15,07:25:00,6.54,6.85,,9,7,,91199,,93399,,92299</data90>
    <data91>2024-02-15,07:30:00,6.55,6.85,,9,7,,91199,,93399,,92299</data91>
    <data92>2024-02-15,07:35:00,6.55,6.85,,9,7,,91199,,93399,,92299</data92>
    <data93>2024-02-15,07:40:00,6.55,6.85,,9,7,,91199,,93399,,92299</data93>
    <data94>2024-02-15,07:45:00,6.55,6.85,,9,7,,91199,,93399,,92299</data94>
    <data95>2024-02-15,07:50:00,6.54,6.86,,9,7,,91199,,93399,,92299</data95>
    <data96>2024-02-15,07:55:00,6.55,6.86,,9,7,,91199,,93399,,92299</data96>
    <data97>2024-02-15,08:00:00,6.54,6.86,,9,7,,91199,,93399,,92299</data97>
    <data98>2024-02-15,08:05:00,6.55,6.85,,9,7,,91199,,93399,,92299</data98>
    <data99>2024-02-15,08:10:00,6.54,6.85,,9,7,,91199,,93399,,92299</data99>
    <data100>2024-02-15,08:15:00,6.55,6.85,,9,7,,91199,,93399,,92299</data100>
    <data101>2024-02-15,08:20:00,6.55,6.85,,9,7,,91199,,93399,,92299</data101>
    <data102>2024-02-15,08:25:00,6.54,6.85,,9,7,,91199,,93399,,92299</data102>
    <data103>2024-02-15,08:30:00,6.54,6.85,,9,7,,91199,,93399,,92299</data103>
    <data104>2024-02-15,08:35:00,6.54,6.84,,9,7,,91199,,93399,,92299</data104>
    <data105>2024-02-15,08:40:00,6.54,6.84,,9,7,,91199,,93399,,92299</data105>
    <data106>2024-02-15,08:45:00,6.53,6.84,,9,7,,91199,,93399,,92299</data106>
    <data107>2024-02-15,08:50:00,6.52,6.83,,9,7,,91199,,93399,,92299</data107>
    <data108>2024-02-15,08:55:00,6.52,6.83,,9,7,,91199,,93399,,92299</data108>
    <data109>2024-02-15,09:00:00,6.52,6.83,,9,7,,91199,,93399,,92299</data109>
    <data110>2024-02-15,09:05:00,6.52,6.83,,9,7,,91199,,93399,,92299</data110>
    <data111>2024-02-15,09:10:00,6.52,6.82,,9,7,,91199,,93399,,92299</data111>
    <data112>2024-02-15,09:15:00,6.52,6.82,,9,7,,91199,,93399,,92299</data112>
    <data113>2024-02-15,09:20:00,6.51,6.82,,9,7,,91199,,93399,,92299</data113>
    <data114>2024-02-15,09:25:00,6.51,6.82,,9,7,,91199,,93399,,92299</data114>
    <data115>2024-02-15,09:30:00,6.51,6.82,,9,7,,91199,,93399,,92299</data115>
    <data116>2024-02-15,09:35:00,6.51,6.82,,9,7,,91199,,93399,,92299</data116>
    <data117>2024-02-15,09:40:00,6.51,6.82,,9,7,,91199,,93399,,92299</data117>
    <data118>2024-02-15,09:45:00,6.51,6.82,,9,7,,91199,,93399,,92299</data118>
    <data119>2024-02-15,09:50:00,6.51,6.82,,9,7,,91199,,93399,,92299</data119>
    <data120>2024-02-15,09:55:00,6.51,6.82,,9,7,,91199,,93399,,92299</data120>
    <data121>2024-02-15,10:00:00,6.51,6.82,,9,7,,91199,,93399,,92299</data121>
    <data122>2024-02-15,10:05:00,6.51,6.82,,9,7,,91199,,93399,,92299</data122>
    <data123>2024-02-15,10:10:00,6.51,6.83,,9,7,,91199,,93399,,92299</data123>
    <data124>2024-02-15,10:15:00,6.51,6.82,,9,7,,91199,,93399,,92299</data124>
    <data125>2024-02-15,10:20:00,6.51,6.83,,9,7,,91199,,93399,,92299</data125>
    <data126>2024-02-15,10:25:00,6.51,6.83,,9,7,,91199,,93399,,92299</data126>
    <data127>2024-02-15,10:30:00,6.51,6.83,,9,7,,91199,,93399,,92299</data127>
    <data128>2024-02-15,10:35:00,6.51,6.84,,9,7,,91199,,93399,,92299</data128>
    <data129>2024-02-15,10:40:00,6.51,6.83,,9,7,,91199,,93399,,92299</data129>
    <data130>2024-02-15,10:45:00,6.51,6.84,,9,7,,91199,,93399,,92299</data130>
    <data131>2024-02-15,10:50:00,6.51,6.83,,9,7,,91199,,93399,,92299</data131>
    <data132>2024-02-15,10:55:00,6.51,6.83,,9,7,,91199,,93399,,92299</data132>
    <data133>2024-02-15,11:00:00,6.51,6.84,,9,7,,91199,,93399,,92299</data133>
    <data134>2024-02-15,11:05:00,6.51,6.83,,9,7,,91199,,93399,,92299</data134>
    <data135>2024-02-15,11:10:00,6.51,6.82,,9,7,,91199,,93399,,92299</data135>
    <data136>2024-02-15,11:15:00,6.51,6.82,,9,7,,91199,,93399,,92299</data136>
    <data137>2024-02-15,11:20:00,6.51,6.82,,9,7,,91199,,93399,,92299</data137>
    <data138>2024-02-15,11:25:00,6.51,6.83,,9,7,,91199,,93399,,92299</data138>
    <data139>2024-02-15,11:30:00,6.51,6.83,,9,7,,91199,,93399,,92299</data139>
    <data140>2024-02-15,11:35:00,6.51,6.83,,9,7,,91199,,93399,,92299</data140>
    <data141>2024-02-15,11:40:00,6.51,6.82,,9,7,,91199,,93399,,92299</data141>
    <data142>2024-02-15,11:45:00,6.51,6.82,,9,7,,91199,,93399,,92299</data142>
    <data143>2024-02-15,11:50:00,6.51,6.82,,9,7,,91199,,93399,,92299</data143>
    <data144>2024-02-15,11:55:00,6.51,6.82,,9,7,,91199,,93399,,92299</data144>
    <data145>2024-02-15,12:00:00,6.51,6.82,,9,7,,91199,,93399,,92299</data145>
    <data146>2024-02-15,12:05:00,6.51,6.82,,9,7,,91199,,93399,,92299</data146>
    <data147>2024-02-15,12:10:00,6.51,6.82,,9,7,,91199,,93399,,92299</data147>
    <data148>2024-02-15,12:15:00,6.51,6.82,,9,7,,91199,,93399,,92299</data148>
    <data149>2024-02-15,12:20:00,6.51,6.82,,9,7,,91199,,93399,,92299</data149>
    <data150>2024-02-15,12:25:00,6.51,6.82,,9,7,,91199,,93399,,92299</data150>
    <data151>2024-02-15,12:30:00,6.51,6.82,,9,7,,91199,,93399,,92299</data151>
    <data152>2024-02-15,12:35:00,6.51,6.83,,9,7,,91199,,93399,,92299</data152>
  </logging>
  <status>
    <message>Complete</message>
  </status>
</LOGGING>